{
  "@id": "/templates/site-footer",
  "@type": "Document",
  "UID": "site-footer-uid",
  "id": "site-footer",
  "review_state": "published",
  "title": "Site Footer",
  "description": "Footer with social links and copyright",
  "blocks": {
    "footer-social": {
      "@type": "socialLinks",
      "fixed": true,
      "readOnly": true,
      "templateId": "/templates/site-footer",
      "templateInstanceId": "site-footer-def-instance",
      "placeholder": "social",
      "links": [
        { "@id": "link-1", "url": "https://github.com/collective/volto-hydra", "fixed": true, "readOnly": true, "templateId": "/templates/site-footer", "templateInstanceId": "site-footer-def-instance" },
        { "@id": "link-2", "url": "https://discord.gg/plone", "fixed": true, "readOnly": true, "templateId": "/templates/site-footer", "templateInstanceId": "site-footer-def-instance" },
        { "@id": "link-3", "url": "https://plone.org", "fixed": true, "readOnly": true, "templateId": "/templates/site-footer", "templateInstanceId": "site-footer-def-instance" },
        { "@id": "link-4", "url": "https://www.youtube.com/@plonecms", "fixed": true, "readOnly": true, "templateId": "/templates/site-footer", "templateInstanceId": "site-footer-def-instance" }
      ]
    },
    "footer-copyright": {
      "@type": "slate",
      "fixed": true,
      "readOnly": true,
      "templateId": "/templates/site-footer",
      "templateInstanceId": "site-footer-def-instance",
      "placeholder": "copyright",
      "value": [
        {
          "type": "p",
          "children": [
            { "text": "Hydra — visual editing for headless Plone. © 2024-2026 Plone Foundation." }
          ]
        }
      ],
      "plaintext": "Hydra — visual editing for headless Plone. © 2024-2026 Plone Foundation."
    },
    "default-slot": {
      "@type": "slate",
      "templateId": "/templates/site-footer",
      "templateInstanceId": "site-footer-def-instance",
      "placeholder": "default",
      "value": [
        {
          "type": "p",
          "children": [{ "text": "" }]
        }
      ],
      "plaintext": ""
    }
  },
  "blocks_layout": {
    "items": ["footer-social", "footer-copyright", "default-slot"]
  },
  "@components": {
    "actions": {
      "@id": "/templates/site-footer/@actions",
      "object": [
        {
          "@id": "/templates/site-footer/edit",
          "id": "edit",
          "title": "Edit"
        }
      ],
      "object_buttons": []
    },
    "breadcrumbs": {
      "@id": "/templates/site-footer/@breadcrumbs",
      "items": [
        { "@id": "/templates", "title": "Templates" },
        { "@id": "/templates/site-footer", "title": "Site Footer" }
      ]
    }
  }
}
